picomon/__init__.py
picomon/__main__.py
picomon/app.py
picomon/config.py
picomon/history.py
picomon/monitor.py
picomon/smi.py
picomon/system_info.py
picomon/ui.py
picomon/providers/__init__.py
picomon/providers/amd.py
picomon/providers/apple.py
picomon/providers/base.py
picomon/providers/nvidia.py
picomon/screens/__init__.py
picomon/screens/dashboard.py
picomon/screens/gpu_detail.py
picomon/screens/rig_card.py
picomon/screens/system.py
picomon/styles/app.tcss
picomon/widgets/__init__.py
picomon/widgets/gpu_card.py
picomon/widgets/metric_bar.py
picomon/widgets/sparkline.py
picomon/widgets/stat_box.py
picomon-0.2.1.dist-info/licenses/LICENSE
picomon-0.2.1.dist-info/METADATA
picomon-0.2.1.dist-info/WHEEL
picomon-0.2.1.dist-info/entry_points.txt
picomon-0.2.1.dist-info/top_level.txt
picomon-0.2.1.dist-info/RECORD
