Metadata-Version: 2.4
Name: picomon
Version: 0.2.1
Summary: Beautiful TUI dashboard for monitoring GPUs (AMD, NVIDIA, Apple Silicon)
Author-email: Omar Kamali <picomon@omarkama.li>
License: MIT License
Project-URL: Homepage, https://github.com/omarkamali/picomon
Project-URL: Issues, https://github.com/omarkamali/picomon/issues
Project-URL: Repository, https://github.com/omarkamali/picomon
Keywords: gpu,monitor,cli,tui,textual,amd,nvidia,apple-silicon
Classifier: Development Status :: 4 - Beta
Classifier: Environment :: Console
Classifier: Intended Audience :: System Administrators
Classifier: Intended Audience :: Developers
Classifier: License :: OSI Approved :: MIT License
Classifier: Operating System :: POSIX
Classifier: Programming Language :: Python
Classifier: Programming Language :: Python :: 3
Classifier: Programming Language :: Python :: 3.9
Classifier: Programming Language :: Python :: 3.10
Classifier: Programming Language :: Python :: 3.11
Classifier: Programming Language :: Python :: 3.12
Classifier: Topic :: System :: Monitoring
Requires-Python: >=3.9
License-File: LICENSE
Requires-Dist: textual>=0.89.0
Requires-Dist: psutil>=5.9.0
Requires-Dist: pyperclip>=1.8.0
Provides-Extra: dev
Requires-Dist: pytest>=7; extra == "dev"
Dynamic: license-file
